nxtransit/__init__.py
nxtransit/accessibility.py
nxtransit/connectors.py
nxtransit/converters.py
nxtransit/frequency.py
nxtransit/functions.py
nxtransit/loaders.py
nxtransit/other.py
nxtransit/routers.py
nxtransit-0.4.1.dist-info/METADATA
nxtransit-0.4.1.dist-info/WHEEL
nxtransit-0.4.1.dist-info/licenses/LICENSE
nxtransit-0.4.1.dist-info/RECORD
