Metadata-Version: 2.3
Name: NxTransit
Version: 0.4.1
Summary: Construct and analyze time-dependent transit networks from GTFS data
Author: Chingiz Zhanarbaev
License: MIT License
License-File: LICENSE
Classifier: Development Status :: 3 - Alpha
Classifier: Intended Audience :: Science/Research
Classifier: License :: OSI Approved :: MIT License
Classifier: Operating System :: MacOS
Classifier: Operating System :: Microsoft :: Windows
Classifier: Operating System :: POSIX :: Linux
Classifier: Programming Language :: Python
Classifier: Programming Language :: Python :: 3.10
Classifier: Programming Language :: Python :: 3.11
Classifier: Programming Language :: Python :: 3.12
Classifier: Topic :: Scientific/Engineering :: GIS
Classifier: Topic :: Scientific/Engineering :: Information Analysis
Classifier: Topic :: Scientific/Engineering :: Visualization
Requires-Python: >=3.10
Requires-Dist: geocube>=0.5.0
Requires-Dist: geopandas>=0.14.0
Requires-Dist: networkx>=3.2.0
Requires-Dist: numpy<2.0.0,>=1.26.0
Requires-Dist: osmnx>=1.9
Requires-Dist: pandas>=2.0
Requires-Dist: scipy>=1.12.0
Requires-Dist: shapely>=2.0
Provides-Extra: docs
Requires-Dist: myst-nb; extra == 'docs'
Requires-Dist: sphinx-book-theme; extra == 'docs'
Requires-Dist: sphinx==7.2.6; extra == 'docs'
Provides-Extra: tests
Requires-Dist: pytest>=8.0.1; extra == 'tests'
